Metadata-Version: 2.1
Name: example-package-walnutor
Version: 1.0
Summary: example package walnutor library
Home-page: https://github.com
Author: TaoHe
Author-email: super_super_tao@163.com
License: Apache 2.0
Keywords: example
Classifier: Development Status :: 3 - Alpha
Classifier: Intended Audience :: Developers
Classifier: Programming Language :: Python :: 3
Classifier: Programming Language :: Python :: 3.7
Classifier: Programming Language :: Python :: 3.8
Classifier: Programming Language :: Python :: 3.9
Classifier: Programming Language :: Python :: 3.10
Classifier: Programming Language :: Python :: 3 :: Only
Classifier: License :: OSI Approved :: MIT License
Classifier: Operating System :: OS Independent
